inference_activity_requests/__init__.py
inference_activity_requests-1.0.2.dist-info/METADATA
inference_activity_requests-1.0.2.dist-info/WHEEL
inference_activity_requests-1.0.2.dist-info/top_level.txt
inference_activity_requests-1.0.2.dist-info/RECORD
