Metadata-Version: 2.2
Name: inference-activity-requests
Version: 1.0.2
Summary: Requests hooks for tracking inference activities on Heroku AI
Author: Add Co
License: MIT
Project-URL: Homepage, https://github.com/add-co/inference-activity-requests
Classifier: Programming Language :: Python :: 3
Classifier: License :: OSI Approved :: MIT License
Classifier: Operating System :: OS Independent
Requires-Python: >=3.7
Requires-Dist: requests>=2.25.0
Dynamic: requires-python
